README.md
setup.py
src/pymautic/__init__.py
src/pymautic/api.py
src/pymautic.egg-info/PKG-INFO
src/pymautic.egg-info/SOURCES.txt
src/pymautic.egg-info/dependency_links.txt
src/pymautic.egg-info/entry_points.txt
src/pymautic.egg-info/not-zip-safe
src/pymautic.egg-info/requires.txt
src/pymautic.egg-info/top_level.txt