Metadata-Version: 1.0
Name: pymautic
Version: 0.22
Summary: Python Mautic API
Home-page: https://github.com/tachang/pymautic
Author: Jeff Tchang
Author-email: jeff.tchang@gmail.com
License: UNKNOWN
Keywords: mautic api
Platform: UNKNOWN
